django_extensions_shell/__init__.py
django_extensions_shell/models.py
django_extensions_shell/management/__init__.py
django_extensions_shell/management/shells.py
django_extensions_shell/management/signals.py
django_extensions_shell/management/utils.py
django_extensions_shell/management/commands/__init__.py
django_extensions_shell/management/commands/shell_plus.py
django_extensions_shell-1.7.4.1.dist-info/DESCRIPTION.rst
django_extensions_shell-1.7.4.1.dist-info/LICENSE.txt
django_extensions_shell-1.7.4.1.dist-info/METADATA
django_extensions_shell-1.7.4.1.dist-info/RECORD
django_extensions_shell-1.7.4.1.dist-info/WHEEL
django_extensions_shell-1.7.4.1.dist-info/metadata.json
django_extensions_shell-1.7.4.1.dist-info/top_level.txt
tests/__init__.py
tests/test_shellplus_command.py
tests/testapp/__init__.py
tests/testapp/apps.py
tests/testapp/models.py
tests/testapp/settings.py
tests/testapp/urls.py
